pubkeeper/server/websocket/__init__.py
pubkeeper/server/websocket/packet.py
pubkeeper/server/websocket/pool.py
pubkeeper/server/websocket/server.py
pubkeeper.server.websocket-1.0.0.dist-info/DESCRIPTION.rst
pubkeeper.server.websocket-1.0.0.dist-info/METADATA
pubkeeper.server.websocket-1.0.0.dist-info/RECORD
pubkeeper.server.websocket-1.0.0.dist-info/WHEEL
pubkeeper.server.websocket-1.0.0.dist-info/entry_points.txt
pubkeeper.server.websocket-1.0.0.dist-info/metadata.json
pubkeeper.server.websocket-1.0.0.dist-info/top_level.txt
